bip85/BIP85DRNG.py
bip85/__init__.py
bip85/app.py
bip85/bip85.py
bip85/extras.py
bip85-0.2.0.dist-info/LICENSE
bip85-0.2.0.dist-info/METADATA
bip85-0.2.0.dist-info/WHEEL
bip85-0.2.0.dist-info/top_level.txt
bip85-0.2.0.dist-info/RECORD
